LICENSE
MANIFEST.in
README.md
setup.cfg
setup.py
netty_finder/__init__.py
netty_finder.egg-info/PKG-INFO
netty_finder.egg-info/SOURCES.txt
netty_finder.egg-info/dependency_links.txt
netty_finder.egg-info/top_level.txt